{
  "version": "7",
  "dialect": "postgresql",
  "entries": [
    {
      "idx": 0,
      "version": "7",
      "when": 1766723736792,
      "tag": "0000_broken_doctor_spectrum",
      "breakpoints": true
    },
    {
      "idx": 1,
      "version": "7",
      "when": 1766793357172,
      "tag": "0001_outstanding_marvel_zombies",
      "breakpoints": true
    },
    {
      "idx": 2,
      "version": "7",
      "when": 1767207924643,
      "tag": "0002_real_starfox",
      "breakpoints": true
    }
  ]
}